CHANGES.rst
DESCRIPTION.rst
LICENSE
MANIFEST.in
README.md
setup.py
src/happy/logo.png
src/happy/tkinter/__init__.py
src/happy/tkinter/_cursor_utils.py
src/happy/tkinter/_modifiers.py
src/happy/tkinter/_threads.py
src/happy/tkinter/_tooltip.py
src/happy/tkinter/_undo.py
src/happy/tkinter/data_viewer/__init__.py
src/happy/tkinter/data_viewer/_session.py
src/happy/tkinter/data_viewer/viewer.py
src/happy/tkinter/data_viewer/viewer.ui
src/happy/tkinter/data_viewer/viewer_old.py
src/happy/tkinter/dialog/__init__.py
src/happy/tkinter/dialog/_querylist.py
src/happy/tkinter/dialog/text_dialog.py
src/happy/tkinter/dialog/text_dialog.ui
src/happy/tkinter/envi_viewer/__init__.py
src/happy/tkinter/envi_viewer/_annotations.py
src/happy/tkinter/envi_viewer/_redis.py
src/happy/tkinter/envi_viewer/_session.py
src/happy/tkinter/envi_viewer/annotations.py
src/happy/tkinter/envi_viewer/annotations.ui
src/happy/tkinter/envi_viewer/image.py
src/happy/tkinter/envi_viewer/image.ui
src/happy/tkinter/envi_viewer/sub_images.py
src/happy/tkinter/envi_viewer/sub_images.ui
src/happy/tkinter/envi_viewer/viewer.py
src/happy/tkinter/envi_viewer/viewer.ui
src/happy/tkinter/raw_checker/__init__.py
src/happy/tkinter/raw_checker/_session.py
src/happy/tkinter/raw_checker/checker.py
src/happy/tkinter/raw_checker/checker.ui
src/happy_tools_tkinter.egg-info/PKG-INFO
src/happy_tools_tkinter.egg-info/SOURCES.txt
src/happy_tools_tkinter.egg-info/dependency_links.txt
src/happy_tools_tkinter.egg-info/entry_points.txt
src/happy_tools_tkinter.egg-info/requires.txt
src/happy_tools_tkinter.egg-info/top_level.txt