Metadata-Version: 2.1
Name: happy-tools-tkinter
Version: 0.0.1
Summary: tkinter user interface for the happy-tools library.
Home-page: https://github.com/wairas/happy-tools-tkinter
Author: Peter Reutemann
Author-email: fracpete@waikato.ac.nz
License: MIT License
Classifier: Development Status :: 4 - Beta
Classifier: License :: OSI Approved :: MIT License
Classifier: Topic :: Scientific/Engineering
Classifier: Programming Language :: Python :: 3
License-File: LICENSE
